cmasher/__init__.py
cmasher/__version__.py
cmasher/_handlercolorpolycollection.py
cmasher/_known_cmap_types.py
cmasher/app_usage.py
cmasher/cli_tools.py
cmasher/cm.py
cmasher/cm.pyi
cmasher/utils.py
cmasher/colormaps/app_data.txt.gz
cmasher/colormaps/cm_amber.npy
cmasher/colormaps/cm_amethyst.npy
cmasher/colormaps/cm_apple.npy
cmasher/colormaps/cm_arctic.npy
cmasher/colormaps/cm_bubblegum.npy
cmasher/colormaps/cm_chroma.npy
cmasher/colormaps/cm_copper.npy
cmasher/colormaps/cm_cosmic.npy
cmasher/colormaps/cm_dusk.npy
cmasher/colormaps/cm_eclipse.npy
cmasher/colormaps/cm_ember.npy
cmasher/colormaps/cm_emerald.npy
cmasher/colormaps/cm_emergency.npy
cmasher/colormaps/cm_fall.npy
cmasher/colormaps/cm_flamingo.npy
cmasher/colormaps/cm_freeze.npy
cmasher/colormaps/cm_fusion.npy
cmasher/colormaps/cm_gem.npy
cmasher/colormaps/cm_ghostlight.npy
cmasher/colormaps/cm_gothic.npy
cmasher/colormaps/cm_guppy.npy
cmasher/colormaps/cm_holly.npy
cmasher/colormaps/cm_horizon.npy
cmasher/colormaps/cm_iceburn.npy
cmasher/colormaps/cm_infinity.npy
cmasher/colormaps/cm_jungle.npy
cmasher/colormaps/cm_lavender.npy
cmasher/colormaps/cm_lilac.npy
cmasher/colormaps/cm_neon.npy
cmasher/colormaps/cm_neutral.npy
cmasher/colormaps/cm_nuclear.npy
cmasher/colormaps/cm_ocean.npy
cmasher/colormaps/cm_pepper.npy
cmasher/colormaps/cm_pride.npy
cmasher/colormaps/cm_prinsenvlag.npy
cmasher/colormaps/cm_rainforest.npy
cmasher/colormaps/cm_redshift.npy
cmasher/colormaps/cm_sapphire.npy
cmasher/colormaps/cm_savanna.npy
cmasher/colormaps/cm_seasons.npy
cmasher/colormaps/cm_seaweed.npy
cmasher/colormaps/cm_sepia.npy
cmasher/colormaps/cm_sunburst.npy
cmasher/colormaps/cm_swamp.npy
cmasher/colormaps/cm_torch.npy
cmasher/colormaps/cm_toxic.npy
cmasher/colormaps/cm_tree.npy
cmasher/colormaps/cm_tropical.npy
cmasher/colormaps/cm_viola.npy
cmasher/colormaps/cm_voltage.npy
cmasher/colormaps/cm_waterlily.npy
cmasher/colormaps/cm_watermelon.npy
cmasher/colormaps/cm_wildfire.npy
cmasher/colormaps/prep_cmap_data.py
cmasher-1.9.1.dist-info/METADATA
cmasher-1.9.1.dist-info/WHEEL
cmasher-1.9.1.dist-info/entry_points.txt
cmasher-1.9.1.dist-info/licenses/LICENSE
cmasher-1.9.1.dist-info/RECORD
