Metadata-Version: 2.3
Name: cmasher
Version: 1.9.1
Summary: Scientific colormaps for making accessible, informative and 'cmashing' plots
Project-URL: Homepage, https://cmasher.readthedocs.io
Project-URL: Documentation, https://cmasher.readthedocs.io
Project-URL: Source Code, https://github.com/1313e/CMasher
Author-email: Ellert van der Velden <ellert_vandervelden@outlook.com>
License: BSD-3
Keywords: cmasher perceptually uniform sequential colormaps plotting python visualization
Classifier: Development Status :: 5 - Production/Stable
Classifier: Framework :: Matplotlib
Classifier: Intended Audience :: Developers
Classifier: License :: OSI Approved :: BSD License
Classifier: Natural Language :: English
Classifier: Operating System :: MacOS
Classifier: Operating System :: Microsoft :: Windows
Classifier: Operating System :: Unix
Classifier: Programming Language :: Python
Classifier: Programming Language :: Python :: 3
Classifier: Programming Language :: Python :: 3.10
Classifier: Programming Language :: Python :: 3.11
Classifier: Programming Language :: Python :: 3.12
Classifier: Programming Language :: Python :: 3.13
Classifier: Topic :: Scientific/Engineering :: Visualization
Classifier: Topic :: Utilities
Requires-Python: <4,>=3.10
Requires-Dist: colorspacious>=1.1.0
Requires-Dist: matplotlib>=3.5
Requires-Dist: numpy>=1.21.2
